AUTHORS.rst
CONTRIBUTING.rst
HISTORY.rst
LICENSE
MANIFEST.in
README.rst
setup.py
bidiutils/__init__.py
bidiutils/context_processors.py
bidiutils/models.py
bidiutils/templatetags/__init__.py
bidiutils/templatetags/bidiutils_tags.py
django_bidi_utils.egg-info/PKG-INFO
django_bidi_utils.egg-info/SOURCES.txt
django_bidi_utils.egg-info/dependency_links.txt
django_bidi_utils.egg-info/not-zip-safe
django_bidi_utils.egg-info/top_level.txt