Metadata-Version: 1.1
Name: django-bidi-utils
Version: 1.0
Summary: context processors and filters for handling Bi-directional (BiDi) in django templates
Home-page: https://github.com/MeirKriheli/django-bidi-utils
Author: Meir Kriheli
Author-email: mkriheli@gmail.com
License: MIT
Keywords: django-bidi-utils
Platform: UNKNOWN
Classifier: Development Status :: 5 - Production/Stable
Classifier: Framework :: Django
Classifier: Intended Audience :: Developers
Classifier: License :: OSI Approved :: MIT License
Classifier: Natural Language :: English
Classifier: Programming Language :: Python :: 2
Classifier: Programming Language :: Python :: 2.6
Classifier: Programming Language :: Python :: 2.7
Classifier: Programming Language :: Python :: 3
Classifier: Programming Language :: Python :: 3.3
